Metadata-Version: 2.1
Name: quantiphyse-qbold
Version: 0.9.1.post4
Summary: Quantiphyse plugin for qBOLD-MRI data
Home-page: https://quantiphyse.readthedocs.io/
Author: Martin Craig
Author-email: martin.craig@eng.ox.ac.uk
License: Apache-2.0
Platform: UNKNOWN
Classifier: Development Status :: 3 - Alpha
Classifier: Intended Audience :: Science/Research
Classifier: Programming Language :: Python :: 2.7
Classifier: Programming Language :: Python :: 3
Classifier: Topic :: Scientific/Engineering :: Bio-Informatics
Classifier: License :: OSI Approved :: Apache Software License
License-File: LICENSE
